README.md
setup.py
pipproj/__init__.py
pipproj.egg-info/PKG-INFO
pipproj.egg-info/SOURCES.txt
pipproj.egg-info/dependency_links.txt
pipproj.egg-info/requires.txt
pipproj.egg-info/top_level.txt