Metadata-Version: 2.1
Name: pipproj
Version: 0.1.0
Summary: CLI utility to help you manage you python project like npm
Home-page: https://github.com/yogesh-aggarwal/pipproj
Author: Yogesh Aggarwal
Author-email: yogeshdev@gmail.com
License: AGPL 3.0
Download-URL: https://raw.githubusercontent.com/yogesh-aggarwal/pipproj/master/dist/pipproj-0.1.0.tar.gz
Keywords: CLI,Environment,Management
Platform: UNKNOWN
Classifier: Development Status :: 5 - Production/Stable
Classifier: Intended Audience :: Developers
Classifier: Programming Language :: Python :: 3
Classifier: Programming Language :: Python :: 3.4
Classifier: Programming Language :: Python :: 3.5
Classifier: Programming Language :: Python :: 3.6
Classifier: Programming Language :: Python :: 3.7
Classifier: Programming Language :: Python :: 3.8
